plugs_store/__init__.py
plugs_store/apps.py
plugs_store/exceptions.py
plugs_store/models.py
plugs_store/signals.py
plugs_store/urls.py
plugs_store/views.py
plugs_store/migrations/0001_initial.py
plugs_store/migrations/__init__.py
plugs_store/payments/ifthenpay/models.py
plugs_store/payments/paypal/models.py
plugs_store/static/css/plugs_store.css
plugs_store/static/js/plugs_store.js
plugs_store/templates/plugs_store/base.html
plugs_store-0.3.0.dist-info/DESCRIPTION.rst
plugs_store-0.3.0.dist-info/METADATA
plugs_store-0.3.0.dist-info/RECORD
plugs_store-0.3.0.dist-info/WHEEL
plugs_store-0.3.0.dist-info/metadata.json
plugs_store-0.3.0.dist-info/top_level.txt
