Metadata-Version: 2.0
Name: plugs-store
Version: 0.3.0
Summary: Reusable REST Store
Home-page: https://github.com/ricardolobo/plugs-store
Author: Ricardo Lobo
Author-email: ricardolobo@solo.com.pt
License: MIT
Keywords: plugs-store
Platform: UNKNOWN
Classifier: Development Status :: 3 - Alpha
Classifier: Framework :: Django
Classifier: Framework :: Django :: 1.8
Classifier: Framework :: Django :: 1.9
Classifier: Framework :: Django :: 1.10
Classifier: Intended Audience :: Developers
Classifier: License :: OSI Approved :: BSD License
Classifier: Natural Language :: English
Classifier: Programming Language :: Python :: 2
Classifier: Programming Language :: Python :: 2.7
Classifier: Programming Language :: Python :: 3
Classifier: Programming Language :: Python :: 3.3
Classifier: Programming Language :: Python :: 3.4
Classifier: Programming Language :: Python :: 3.5
